Metadata-Version: 2.1
Name: specterext-faucet
Version: 0.1.2
Summary: Specter Desktop extension with a regtest faucet and a miner
Home-page: https://github.com/stepansnigirev/specterext-faucet
Author: Stepan Snigirev
Author-email: snigirev.stepan@gmail.com
License: UNKNOWN
Project-URL: Bug Tracker, https://github.com/stepansnigirev/specterext-faucet/issues
Platform: UNKNOWN
Classifier: Programming Language :: Python :: 3
Classifier: License :: OSI Approved :: MIT License
Classifier: Operating System :: OS Independent
Requires-Python: >=3.6
License-File: LICENSE
